sopel_flipper/__init__.py
sopel_flipper/plugin.py
sopel_flipper/mirror/__init__.py
sopel_flipper/mirror/data.py
sopel_flipper-1.1.0.post0.dist-info/COPYING
sopel_flipper-1.1.0.post0.dist-info/METADATA
sopel_flipper-1.1.0.post0.dist-info/WHEEL
sopel_flipper-1.1.0.post0.dist-info/entry_points.txt
sopel_flipper-1.1.0.post0.dist-info/top_level.txt
sopel_flipper-1.1.0.post0.dist-info/RECORD
