Metadata-Version: 2.1
Name: sopel-flipper
Version: 1.1.0.post0
Summary: A Sopel plugin to flip (and mirror) text
Author-email: dgw <dgw@technobabbl.es>
License: EFL-2.0
Project-URL: Homepage, https://github.com/dgw/sopel-flipper
Project-URL: Bug Tracker, https://github.com/dgw/sopel-flipper/issues
Keywords: sopel,plugin,bot,irc
Platform: Linux x86, x86-64
Classifier: Intended Audience :: Developers
Classifier: Intended Audience :: System Administrators
Classifier: License :: Eiffel Forum License (EFL)
Classifier: License :: OSI Approved :: Eiffel Forum License
Classifier: Programming Language :: Python :: 3 :: Only
Classifier: Topic :: Communications :: Chat :: Internet Relay Chat
Requires-Python: <4,>=3.8
License-File: COPYING
Requires-Dist: sopel>=7.1
Requires-Dist: upsidedown==0.4
